slick_siphon/__init__.py
slick_siphon-0.1.2.dist-info/METADATA
slick_siphon-0.1.2.dist-info/WHEEL
slick_siphon-0.1.2.dist-info/top_level.txt
slick_siphon-0.1.2.dist-info/RECORD
