Metadata-Version: 2.1
Name: slick-siphon
Version: 0.1.2
Summary: The clean way to extend existing functions
Home-page: https://github.com/jeff-hykin/slick_siphon.git
Author: Jeff Hykin
Author-email: jeff.hykin@gmail.com
License: MIT
Platform: UNKNOWN
Requires-Python: >=3.6
